chorecore/__init__.py
chorecore/alphabet.py
chorecore/conditionals.py
chorecore/fraction.py
chorecore/internal.py
chorecore/math.py
chorecore/strings.py
chorecore/symbols.py
chorecore/time.py
chorecore-1.1.0.dist-info/LICENSE
chorecore-1.1.0.dist-info/METADATA
chorecore-1.1.0.dist-info/WHEEL
chorecore-1.1.0.dist-info/top_level.txt
chorecore-1.1.0.dist-info/RECORD
