Metadata-Version: 2.1
Name: chorecore
Version: 1.1.0
Summary: Utilities to simplify many commonly used pieces of code
Home-page: https://github.com/JTSchwartz/chorecore-py
Author: Jacob Schwartz
Author-email: support@chorecore.com
License: ISCL
Download-URL: https://pypi.org/project/chorecore/
Project-URL: Bug Tracker, https://github.com/JTSchwartz/chorecore-py/issues
Keywords: ChoreCore,Chore,Core
Platform: UNKNOWN
Classifier: License :: OSI Approved :: ISC License (ISCL)
Classifier: Natural Language :: English
Classifier: Operating System :: OS Independent
Classifier: Programming Language :: Python :: 3.8
Classifier: Topic :: Utilities
Requires-Python: >=3.8
